cadquery_png_plugin/__init__.py
cadquery_png_plugin/plugin.py
cadquery_png_plugin-1.1.0.dist-info/METADATA
cadquery_png_plugin-1.1.0.dist-info/WHEEL
cadquery_png_plugin-1.1.0.dist-info/licenses/LICENSE
cadquery_png_plugin-1.1.0.dist-info/RECORD
