Metadata-Version: 2.4
Name: cadquery_png_plugin
Version: 1.1.0
Summary: A PNG export plugin for CadQuery.
Project-URL: Repository, https://github.com/jmwright/cadquery-png-plugin.git
Project-URL: Bug Tracker, https://github.com/jmwright/cadquery-png-plugin/issues
Author: Jeremy Wright
Maintainer: Jeremy Wright
License:                                  Apache License
License-File: LICENSE
Keywords: CAD,cadquery,design,engineering
Classifier: Development Status :: 4 - Beta
Classifier: Programming Language :: Python
Requires-Python: >=3.10
Requires-Dist: cadquery
Provides-Extra: dev
Requires-Dist: black; extra == 'dev'
Requires-Dist: pillow; extra == 'dev'
Requires-Dist: pytest; extra == 'dev'
